afvalwijzer_pkg/__init__.py
afvalwijzer_pkg/afvalwijzerapi.py
afvalwijzerapi-0.0.2.dist-info/LICENSE
afvalwijzerapi-0.0.2.dist-info/METADATA
afvalwijzerapi-0.0.2.dist-info/WHEEL
afvalwijzerapi-0.0.2.dist-info/top_level.txt
afvalwijzerapi-0.0.2.dist-info/RECORD
