Metadata-Version: 2.1
Name: afvalwijzerapi
Version: 0.0.2
Summary: Communication package for AfvalwijzerAPI
Home-page: https://github.com/thastealth/afvalwijzer-api
Author: ThaStealth
Author-email: author@example.com
License: UNKNOWN
Platform: UNKNOWN
Classifier: Programming Language :: Python :: 3
Classifier: License :: OSI Approved :: MIT License
Classifier: Operating System :: OS Independent
